README.md
setup.py
JM21008UNO.egg-info/PKG-INFO
JM21008UNO.egg-info/SOURCES.txt
JM21008UNO.egg-info/dependency_links.txt
JM21008UNO.egg-info/requires.txt
JM21008UNO.egg-info/top_level.txt
jm21008uno/__init__.py
jm21008uno/cramer.py
jm21008uno/gauss.py
jm21008uno/gauss_jordan.py
jm21008uno/jacobi.py
jm21008uno/lu_decomposition.py
tests/__init__.py
tests/test_cramer.py
tests/test_gauss.py
tests/test_gauss_jordan.py
tests/test_jacobi.py
tests/test_lu_decomposition.py