Metadata-Version: 2.1
Name: JM21008UNO
Version: 0.1.0
Summary: Librería para resolver sistemas de ecuaciones lineales y no lineales.
Home-page: https://github.com/jeffreyMangandi/JM21008UNO
Author: jeffrey juárez
Author-email: jm21008@ues.edu.sv
License: UNKNOWN
Platform: UNKNOWN
Classifier: Programming Language :: Python :: 3
Classifier: License :: OSI Approved :: MIT License
Classifier: Operating System :: OS Independent
Requires-Python: >=3.6
